{"plant":"braemar","duids":["BRAEMAR1","BRAEMAR2","BRAEMAR3"],"region":"QLD1","month":"2025-12","generatedAt":"2026-04-16T07:07:33.449Z","days":[{"date":"2025-12-01","units":{"BRAEMAR1":{"mwh":0,"runIntervals":0,"runRrpWeighted":0,"runMwTotal":0,"revenue":0},"BRAEMAR2":{"mwh":0,"runIntervals":0,"runRrpWeighted":0,"runMwTotal":0,"revenue":0},"BRAEMAR3":{"mwh":0,"runIntervals":0,"runRrpWeighted":0,"runMwTotal":0,"revenue":0}},"intervals":[]},{"date":"2025-12-02","units":{"BRAEMAR1":{"mwh":0,"runIntervals":0,"runRrpWeighted":0,"runMwTotal":0,"revenue":0},"BRAEMAR2":{"mwh":0,"runIntervals":0,"runRrpWeighted":0,"runMwTotal":0,"revenue":0},"BRAEMAR3":{"mwh":0,"runIntervals":0,"runRrpWeighted":0,"runMwTotal":0,"revenue":0}},"intervals":[]},{"date":"2025-12-03","units":{"BRAEMAR1":{"mwh":0,"runIntervals":0,"runRrpWeighted":0,"runMwTotal":0,"revenue":0},"BRAEMAR2":{"mwh":0,"runIntervals":0,"runRrpWeighted":0,"runMwTotal":0,"revenue":0},"BRAEMAR3":{"mwh":0,"runIntervals":0,"runRrpWeighted":0,"runMwTotal":0,"revenue":0}},"intervals":[]},{"date":"2025-12-04","units":{"BRAEMAR1":{"mwh":0,"runIntervals":0,"runRrpWeighted":0,"runMwTotal":0,"revenue":0},"BRAEMAR2":{"mwh":0,"runIntervals":0,"runRrpWeighted":0,"runMwTotal":0,"revenue":0},"BRAEMAR3":{"mwh":0,"runIntervals":0,"runRrpWeighted":0,"runMwTotal":0,"revenue":0}},"intervals":[]},{"date":"2025-12-05","units":{"BRAEMAR1":{"mwh":0,"runIntervals":0,"runRrpWeighted":0,"runMwTotal":0,"revenue":0},"BRAEMAR2":{"mwh":0,"runIntervals":0,"runRrpWeighted":0,"runMwTotal":0,"revenue":0},"BRAEMAR3":{"mwh":0,"runIntervals":0,"runRrpWeighted":0,"runMwTotal":0,"revenue":0}},"intervals":[]},{"date":"2025-12-06","units":{"BRAEMAR1":{"mwh":0,"runIntervals":0,"runRrpWeighted":0,"runMwTotal":0,"revenue":0},"BRAEMAR2":{"mwh":0,"runIntervals":0,"runRrpWeighted":0,"runMwTotal":0,"revenue":0},"BRAEMAR3":{"mwh":0,"runIntervals":0,"runRrpWeighted":0,"runMwTotal":0,"revenue":0}},"intervals":[]},{"date":"2025-12-07","units":{"BRAEMAR1":{"mwh":0,"runIntervals":0,"runRrpWeighted":0,"runMwTotal":0,"revenue":0},"BRAEMAR2":{"mwh":0,"runIntervals":0,"runRrpWeighted":0,"runMwTotal":0,"revenue":0},"BRAEMAR3":{"mwh":0,"runIntervals":0,"runRrpWeighted":0,"runMwTotal":0,"revenue":0}},"intervals":[]},{"date":"2025-12-08","units":{"BRAEMAR1":{"mwh":0,"runIntervals":0,"runRrpWeighted":0,"runMwTotal":0,"revenue":0},"BRAEMAR2":{"mwh":0,"runIntervals":0,"runRrpWeighted":0,"runMwTotal":0,"revenue":0},"BRAEMAR3":{"mwh":0,"runIntervals":0,"runRrpWeighted":0,"runMwTotal":0,"revenue":0}},"intervals":[]},{"date":"2025-12-09","units":{"BRAEMAR1":{"mwh":0,"runIntervals":0,"runRrpWeighted":0,"runMwTotal":0,"revenue":0},"BRAEMAR2":{"mwh":0,"runIntervals":0,"runRrpWeighted":0,"runMwTotal":0,"revenue":0},"BRAEMAR3":{"mwh":0,"runIntervals":0,"runRrpWeighted":0,"runMwTotal":0,"revenue":0}},"intervals":[]},{"date":"2025-12-10","units":{"BRAEMAR1":{"mwh":0,"runIntervals":0,"runRrpWeighted":0,"runMwTotal":0,"revenue":0},"BRAEMAR2":{"mwh":0,"runIntervals":0,"runRrpWeighted":0,"runMwTotal":0,"revenue":0},"BRAEMAR3":{"mwh":0,"runIntervals":0,"runRrpWeighted":0,"runMwTotal":0,"revenue":0}},"intervals":[]},{"date":"2025-12-11","units":{"BRAEMAR1":{"mwh":0,"runIntervals":0,"runRrpWeighted":0,"runMwTotal":0,"revenue":0},"BRAEMAR2":{"mwh":0,"runIntervals":0,"runRrpWeighted":0,"runMwTotal":0,"revenue":0},"BRAEMAR3":{"mwh":0,"runIntervals":0,"runRrpWeighted":0,"runMwTotal":0,"revenue":0}},"intervals":[]},{"date":"2025-12-12","units":{"BRAEMAR1":{"mwh":0,"runIntervals":0,"runRrpWeighted":0,"runMwTotal":0,"revenue":0},"BRAEMAR2":{"mwh":0,"runIntervals":0,"runRrpWeighted":0,"runMwTotal":0,"revenue":0},"BRAEMAR3":{"mwh":0,"runIntervals":0,"runRrpWeighted":0,"runMwTotal":0,"revenue":0}},"intervals":[]},{"date":"2025-12-13","units":{"BRAEMAR1":{"mwh":0,"runIntervals":0,"runRrpWeighted":0,"runMwTotal":0,"revenue":0},"BRAEMAR2":{"mwh":0,"runIntervals":0,"runRrpWeighted":0,"runMwTotal":0,"revenue":0},"BRAEMAR3":{"mwh":0,"runIntervals":0,"runRrpWeighted":0,"runMwTotal":0,"revenue":0}},"intervals":[]},{"date":"2025-12-14","units":{"BRAEMAR1":{"mwh":0,"runIntervals":0,"runRrpWeighted":0,"runMwTotal":0,"revenue":0},"BRAEMAR2":{"mwh":0,"runIntervals":0,"runRrpWeighted":0,"runMwTotal":0,"revenue":0},"BRAEMAR3":{"mwh":0,"runIntervals":0,"runRrpWeighted":0,"runMwTotal":0,"revenue":0}},"intervals":[]},{"date":"2025-12-15","units":{"BRAEMAR1":{"mwh":612.0044983333333,"runIntervals":49,"runRrpWeighted":1248010.0819870513,"runMwTotal":7344.0539800000015,"revenue":104000.8401655876},"BRAEMAR2":{"mwh":0,"runIntervals":0,"runRrpWeighted":0,"runMwTotal":0,"revenue":0},"BRAEMAR3":{"mwh":0,"runIntervals":0,"runRrpWeighted":0,"runMwTotal":0,"revenue":0}},"intervals":[{"t":"2025-12-15T15:10:00","rrp":250.01,"units":{"BRAEMAR1":46.90754,"BRAEMAR2":0,"BRAEMAR3":0}},{"t":"2025-12-15T15:15:00","rrp":241.22,"units":{"BRAEMAR1":90.18855,"BRAEMAR2":0,"BRAEMAR3":0}},{"t":"2025-12-15T15:20:00","rrp":235.5,"units":{"BRAEMAR1":133.14079,"BRAEMAR2":0,"BRAEMAR3":0}},{"t":"2025-12-15T15:25:00","rrp":235.5,"units":{"BRAEMAR1":152.20979,"BRAEMAR2":0,"BRAEMAR3":0}},{"t":"2025-12-15T15:30:00","rrp":144.5,"units":{"BRAEMAR1":164.72678,"BRAEMAR2":0,"BRAEMAR3":0}},{"t":"2025-12-15T15:35:00","rrp":190.3,"units":{"BRAEMAR1":122.17375,"BRAEMAR2":0,"BRAEMAR3":0}},{"t":"2025-12-15T15:40:00","rrp":190.3,"units":{"BRAEMAR1":138.47166,"BRAEMAR2":0,"BRAEMAR3":0}},{"t":"2025-12-15T15:45:00","rrp":180,"units":{"BRAEMAR1":163.5291,"BRAEMAR2":0,"BRAEMAR3":0}},{"t":"2025-12-15T15:50:00","rrp":234.54,"units":{"BRAEMAR1":163.29424,"BRAEMAR2":0,"BRAEMAR3":0}},{"t":"2025-12-15T15:55:00","rrp":235.5,"units":{"BRAEMAR1":163.83437,"BRAEMAR2":0,"BRAEMAR3":0}},{"t":"2025-12-15T16:00:00","rrp":235.5,"units":{"BRAEMAR1":163.74045,"BRAEMAR2":0,"BRAEMAR3":0}},{"t":"2025-12-15T16:05:00","rrp":235.5,"units":{"BRAEMAR1":163.43515,"BRAEMAR2":0,"BRAEMAR3":0}},{"t":"2025-12-15T16:10:00","rrp":157.95002,"units":{"BRAEMAR1":161.50948,"BRAEMAR2":0,"BRAEMAR3":0}},{"t":"2025-12-15T16:15:00","rrp":234.43,"units":{"BRAEMAR1":163.24728,"BRAEMAR2":0,"BRAEMAR3":0}},{"t":"2025-12-15T16:20:00","rrp":188.22,"units":{"BRAEMAR1":164.44498,"BRAEMAR2":0,"BRAEMAR3":0}},{"t":"2025-12-15T16:25:00","rrp":180,"units":{"BRAEMAR1":164.18665,"BRAEMAR2":0,"BRAEMAR3":0}},{"t":"2025-12-15T16:30:00","rrp":180,"units":{"BRAEMAR1":163.5291,"BRAEMAR2":0,"BRAEMAR3":0}},{"t":"2025-12-15T16:35:00","rrp":190.3,"units":{"BRAEMAR1":164.0927,"BRAEMAR2":0,"BRAEMAR3":0}},{"t":"2025-12-15T16:40:00","rrp":138.05,"units":{"BRAEMAR1":164.42148,"BRAEMAR2":0,"BRAEMAR3":0}},{"t":"2025-12-15T16:45:00","rrp":133,"units":{"BRAEMAR1":163.3647,"BRAEMAR2":0,"BRAEMAR3":0}},{"t":"2025-12-15T16:50:00","rrp":137.95,"units":{"BRAEMAR1":120.67079,"BRAEMAR2":0,"BRAEMAR3":0}},{"t":"2025-12-15T16:55:00","rrp":144.13994,"units":{"BRAEMAR1":165.43127,"BRAEMAR2":0,"BRAEMAR3":0}},{"t":"2025-12-15T17:00:00","rrp":188.22,"units":{"BRAEMAR1":163.66998,"BRAEMAR2":0,"BRAEMAR3":0}},{"t":"2025-12-15T17:05:00","rrp":149.55,"units":{"BRAEMAR1":165.26691,"BRAEMAR2":0,"BRAEMAR3":0}},{"t":"2025-12-15T17:10:00","rrp":143.94002,"units":{"BRAEMAR1":163.27075,"BRAEMAR2":0,"BRAEMAR3":0}},{"t":"2025-12-15T17:15:00","rrp":141.73,"units":{"BRAEMAR1":165.24342,"BRAEMAR2":0,"BRAEMAR3":0}},{"t":"2025-12-15T17:20:00","rrp":133,"units":{"BRAEMAR1":165.10252,"BRAEMAR2":0,"BRAEMAR3":0}},{"t":"2025-12-15T17:25:00","rrp":136.83,"units":{"BRAEMAR1":150.58942,"BRAEMAR2":0,"BRAEMAR3":0}},{"t":"2025-12-15T17:30:00","rrp":188.22,"units":{"BRAEMAR1":165.94795,"BRAEMAR2":0,"BRAEMAR3":0}},{"t":"2025-12-15T17:35:00","rrp":177.9,"units":{"BRAEMAR1":165.66614,"BRAEMAR2":0,"BRAEMAR3":0}},{"t":"2025-12-15T17:40:00","rrp":146.44685,"units":{"BRAEMAR1":163.74045,"BRAEMAR2":0,"BRAEMAR3":0}},{"t":"2025-12-15T17:45:00","rrp":177.9,"units":{"BRAEMAR1":165.76007,"BRAEMAR2":0,"BRAEMAR3":0}},{"t":"2025-12-15T17:50:00","rrp":177.81,"units":{"BRAEMAR1":165.61917,"BRAEMAR2":0,"BRAEMAR3":0}},{"t":"2025-12-15T17:55:00","rrp":157.96,"units":{"BRAEMAR1":163.69347,"BRAEMAR2":0,"BRAEMAR3":0}},{"t":"2025-12-15T18:00:00","rrp":177.9,"units":{"BRAEMAR1":163.43515,"BRAEMAR2":0,"BRAEMAR3":0}},{"t":"2025-12-15T18:05:00","rrp":157.95007,"units":{"BRAEMAR1":163.83437,"BRAEMAR2":0,"BRAEMAR3":0}},{"t":"2025-12-15T18:10:00","rrp":143.94002,"units":{"BRAEMAR1":165.73657,"BRAEMAR2":0,"BRAEMAR3":0}},{"t":"2025-12-15T18:15:00","rrp":137.95,"units":{"BRAEMAR1":166.32368,"BRAEMAR2":0,"BRAEMAR3":0}},{"t":"2025-12-15T18:20:00","rrp":136.82003,"units":{"BRAEMAR1":166.53503,"BRAEMAR2":0,"BRAEMAR3":0}},{"t":"2025-12-15T18:25:00","rrp":143.94002,"units":{"BRAEMAR1":166.53503,"BRAEMAR2":0,"BRAEMAR3":0}},{"t":"2025-12-15T18:30:00","rrp":143.94002,"units":{"BRAEMAR1":166.51155,"BRAEMAR2":0,"BRAEMAR3":0}},{"t":"2025-12-15T18:35:00","rrp":143.94002,"units":{"BRAEMAR1":166.69943,"BRAEMAR2":0,"BRAEMAR3":0}},{"t":"2025-12-15T18:40:00","rrp":177.81,"units":{"BRAEMAR1":166.86383,"BRAEMAR2":0,"BRAEMAR3":0}},{"t":"2025-12-15T18:45:00","rrp":140.98126,"units":{"BRAEMAR1":163.71695,"BRAEMAR2":0,"BRAEMAR3":0}},{"t":"2025-12-15T18:50:00","rrp":125.6885,"units":{"BRAEMAR1":165.76007,"BRAEMAR2":0,"BRAEMAR3":0}},{"t":"2025-12-15T18:55:00","rrp":108.83003,"units":{"BRAEMAR1":114.07178,"BRAEMAR2":0,"BRAEMAR3":0}},{"t":"2025-12-15T19:00:00","rrp":128.39,"units":{"BRAEMAR1":112.16957,"BRAEMAR2":0,"BRAEMAR3":0}},{"t":"2025-12-15T19:05:00","rrp":128.39,"units":{"BRAEMAR1":59.96465,"BRAEMAR2":0,"BRAEMAR3":0}},{"t":"2025-12-15T19:10:00","rrp":138.56995,"units":{"BRAEMAR1":11.77547,"BRAEMAR2":0,"BRAEMAR3":0}}]},{"date":"2025-12-16","units":{"BRAEMAR1":{"mwh":0,"runIntervals":0,"runRrpWeighted":0,"runMwTotal":0,"revenue":0},"BRAEMAR2":{"mwh":0,"runIntervals":0,"runRrpWeighted":0,"runMwTotal":0,"revenue":0},"BRAEMAR3":{"mwh":0,"runIntervals":0,"runRrpWeighted":0,"runMwTotal":0,"revenue":0}},"intervals":[]},{"date":"2025-12-17","units":{"BRAEMAR1":{"mwh":0,"runIntervals":0,"runRrpWeighted":0,"runMwTotal":0,"revenue":0},"BRAEMAR2":{"mwh":0,"runIntervals":0,"runRrpWeighted":0,"runMwTotal":0,"revenue":0},"BRAEMAR3":{"mwh":0,"runIntervals":0,"runRrpWeighted":0,"runMwTotal":0,"revenue":0}},"intervals":[]},{"date":"2025-12-18","units":{"BRAEMAR1":{"mwh":388.63872,"runIntervals":40,"runRrpWeighted":607901.419885445,"runMwTotal":4663.66464,"revenue":50658.45165712041},"BRAEMAR2":{"mwh":0,"runIntervals":0,"runRrpWeighted":0,"runMwTotal":0,"revenue":0},"BRAEMAR3":{"mwh":0,"runIntervals":0,"runRrpWeighted":0,"runMwTotal":0,"revenue":0}},"intervals":[{"t":"2025-12-18T18:50:00","rrp":143.94,"units":{"BRAEMAR1":34.57844,"BRAEMAR2":0,"BRAEMAR3":0}},{"t":"2025-12-18T18:55:00","rrp":128.39,"units":{"BRAEMAR1":77.95338,"BRAEMAR2":0,"BRAEMAR3":0}},{"t":"2025-12-18T19:00:00","rrp":157.95001,"units":{"BRAEMAR1":112.75667,"BRAEMAR2":0,"BRAEMAR3":0}},{"t":"2025-12-18T19:05:00","rrp":127.75,"units":{"BRAEMAR1":153.47794,"BRAEMAR2":0,"BRAEMAR3":0}},{"t":"2025-12-18T19:10:00","rrp":164.46155,"units":{"BRAEMAR1":109.14014,"BRAEMAR2":0,"BRAEMAR3":0}},{"t":"2025-12-18T19:15:00","rrp":163.77,"units":{"BRAEMAR1":161.32159,"BRAEMAR2":0,"BRAEMAR3":0}},{"t":"2025-12-18T19:20:00","rrp":127.75,"units":{"BRAEMAR1":168.34332,"BRAEMAR2":0,"BRAEMAR3":0}},{"t":"2025-12-18T19:25:00","rrp":123.71,"units":{"BRAEMAR1":117.99362,"BRAEMAR2":0,"BRAEMAR3":0}},{"t":"2025-12-18T19:30:00","rrp":122.4,"units":{"BRAEMAR1":109.21059,"BRAEMAR2":0,"BRAEMAR3":0}},{"t":"2025-12-18T19:35:00","rrp":122.4,"units":{"BRAEMAR1":109.44543,"BRAEMAR2":0,"BRAEMAR3":0}},{"t":"2025-12-18T19:40:00","rrp":144.76,"units":{"BRAEMAR1":109.70377,"BRAEMAR2":0,"BRAEMAR3":0}},{"t":"2025-12-18T19:45:00","rrp":127.75,"units":{"BRAEMAR1":155.47408,"BRAEMAR2":0,"BRAEMAR3":0}},{"t":"2025-12-18T19:50:00","rrp":111.58219,"units":{"BRAEMAR1":112.61578,"BRAEMAR2":0,"BRAEMAR3":0}},{"t":"2025-12-18T19:55:00","rrp":121.73,"units":{"BRAEMAR1":110.33781,"BRAEMAR2":0,"BRAEMAR3":0}},{"t":"2025-12-18T20:00:00","rrp":128.39,"units":{"BRAEMAR1":108.71744,"BRAEMAR2":0,"BRAEMAR3":0}},{"t":"2025-12-18T20:05:00","rrp":127.75,"units":{"BRAEMAR1":111.62944,"BRAEMAR2":0,"BRAEMAR3":0}},{"t":"2025-12-18T20:10:00","rrp":127.75,"units":{"BRAEMAR1":108.97575,"BRAEMAR2":0,"BRAEMAR3":0}},{"t":"2025-12-18T20:15:00","rrp":127.76,"units":{"BRAEMAR1":111.51202,"BRAEMAR2":0,"BRAEMAR3":0}},{"t":"2025-12-18T20:20:00","rrp":127.75,"units":{"BRAEMAR1":108.95227,"BRAEMAR2":0,"BRAEMAR3":0}},{"t":"2025-12-18T20:25:00","rrp":127.75,"units":{"BRAEMAR1":111.08931,"BRAEMAR2":0,"BRAEMAR3":0}},{"t":"2025-12-18T20:30:00","rrp":152.57806,"units":{"BRAEMAR1":108.45911,"BRAEMAR2":0,"BRAEMAR3":0}},{"t":"2025-12-18T20:35:00","rrp":107.46304,"units":{"BRAEMAR1":159.34894,"BRAEMAR2":0,"BRAEMAR3":0}},{"t":"2025-12-18T20:40:00","rrp":127.76,"units":{"BRAEMAR1":114.65887,"BRAEMAR2":0,"BRAEMAR3":0}},{"t":"2025-12-18T20:45:00","rrp":157.95,"units":{"BRAEMAR1":109.18712,"BRAEMAR2":0,"BRAEMAR3":0}},{"t":"2025-12-18T20:50:00","rrp":146.44,"units":{"BRAEMAR1":156.67175,"BRAEMAR2":0,"BRAEMAR3":0}},{"t":"2025-12-18T20:55:00","rrp":143.94,"units":{"BRAEMAR1":165.73657,"BRAEMAR2":0,"BRAEMAR3":0}},{"t":"2025-12-18T21:00:00","rrp":133,"units":{"BRAEMAR1":164.06923,"BRAEMAR2":0,"BRAEMAR3":0}},{"t":"2025-12-18T21:05:00","rrp":127.76,"units":{"BRAEMAR1":154.15897,"BRAEMAR2":0,"BRAEMAR3":0}},{"t":"2025-12-18T21:10:00","rrp":128.43404,"units":{"BRAEMAR1":109.18712,"BRAEMAR2":0,"BRAEMAR3":0}},{"t":"2025-12-18T21:15:00","rrp":133,"units":{"BRAEMAR1":110.12648,"BRAEMAR2":0,"BRAEMAR3":0}},{"t":"2025-12-18T21:20:00","rrp":121.40436,"units":{"BRAEMAR1":118.20496,"BRAEMAR2":0,"BRAEMAR3":0}},{"t":"2025-12-18T21:25:00","rrp":129.22664,"units":{"BRAEMAR1":113.55515,"BRAEMAR2":0,"BRAEMAR3":0}},{"t":"2025-12-18T21:30:00","rrp":122.27276,"units":{"BRAEMAR1":108.57654,"BRAEMAR2":0,"BRAEMAR3":0}},{"t":"2025-12-18T21:35:00","rrp":93,"units":{"BRAEMAR1":109.51588,"BRAEMAR2":0,"BRAEMAR3":0}},{"t":"2025-12-18T21:40:00","rrp":103.99,"units":{"BRAEMAR1":109.4924,"BRAEMAR2":0,"BRAEMAR3":0}},{"t":"2025-12-18T21:45:00","rrp":133.63258,"units":{"BRAEMAR1":110.45525,"BRAEMAR2":0,"BRAEMAR3":0}},{"t":"2025-12-18T21:50:00","rrp":123.36079,"units":{"BRAEMAR1":153.40749,"BRAEMAR2":0,"BRAEMAR3":0}},{"t":"2025-12-18T21:55:00","rrp":121.73,"units":{"BRAEMAR1":112.35745,"BRAEMAR2":0,"BRAEMAR3":0}},{"t":"2025-12-18T22:00:00","rrp":115.15,"units":{"BRAEMAR1":61.20929,"BRAEMAR2":0,"BRAEMAR3":0}},{"t":"2025-12-18T22:05:00","rrp":98.73,"units":{"BRAEMAR1":12.05728,"BRAEMAR2":0,"BRAEMAR3":0}}]},{"date":"2025-12-19","units":{"BRAEMAR1":{"mwh":0,"runIntervals":0,"runRrpWeighted":0,"runMwTotal":0,"revenue":0},"BRAEMAR2":{"mwh":0,"runIntervals":0,"runRrpWeighted":0,"runMwTotal":0,"revenue":0},"BRAEMAR3":{"mwh":0,"runIntervals":0,"runRrpWeighted":0,"runMwTotal":0,"revenue":0}},"intervals":[]},{"date":"2025-12-20","units":{"BRAEMAR1":{"mwh":868.8961400000002,"runIntervals":68,"runRrpWeighted":1362116.529287353,"runMwTotal":10426.753679999994,"revenue":113509.710773946},"BRAEMAR2":{"mwh":0,"runIntervals":0,"runRrpWeighted":0,"runMwTotal":0,"revenue":0},"BRAEMAR3":{"mwh":0,"runIntervals":0,"runRrpWeighted":0,"runMwTotal":0,"revenue":0}},"intervals":[{"t":"2025-12-20T16:45:00","rrp":94.34385,"units":{"BRAEMAR1":45.87424,"BRAEMAR2":0,"BRAEMAR3":0}},{"t":"2025-12-20T16:50:00","rrp":76.9934,"units":{"BRAEMAR1":90.5643,"BRAEMAR2":0,"BRAEMAR3":0}},{"t":"2025-12-20T16:55:00","rrp":92.44778,"units":{"BRAEMAR1":115.41037,"BRAEMAR2":0,"BRAEMAR3":0}},{"t":"2025-12-20T17:00:00","rrp":98.73,"units":{"BRAEMAR1":116.37321,"BRAEMAR2":0,"BRAEMAR3":0}},{"t":"2025-12-20T17:05:00","rrp":107.48446,"units":{"BRAEMAR1":108.22427,"BRAEMAR2":0,"BRAEMAR3":0}},{"t":"2025-12-20T17:10:00","rrp":131.30382,"units":{"BRAEMAR1":150.37805,"BRAEMAR2":0,"BRAEMAR3":0}},{"t":"2025-12-20T17:15:00","rrp":128.43276,"units":{"BRAEMAR1":150.11974,"BRAEMAR2":0,"BRAEMAR3":0}},{"t":"2025-12-20T17:20:00","rrp":122.7,"units":{"BRAEMAR1":164.39799,"BRAEMAR2":0,"BRAEMAR3":0}},{"t":"2025-12-20T17:25:00","rrp":141.73,"units":{"BRAEMAR1":164.0927,"BRAEMAR2":0,"BRAEMAR3":0}},{"t":"2025-12-20T17:30:00","rrp":141.73,"units":{"BRAEMAR1":163.95178,"BRAEMAR2":0,"BRAEMAR3":0}},{"t":"2025-12-20T17:35:00","rrp":157.95,"units":{"BRAEMAR1":163.64651,"BRAEMAR2":0,"BRAEMAR3":0}},{"t":"2025-12-20T17:40:00","rrp":220.44242,"units":{"BRAEMAR1":164.2336,"BRAEMAR2":0,"BRAEMAR3":0}},{"t":"2025-12-20T17:45:00","rrp":234.43,"units":{"BRAEMAR1":164.39799,"BRAEMAR2":0,"BRAEMAR3":0}},{"t":"2025-12-20T17:50:00","rrp":157.95,"units":{"BRAEMAR1":163.29424,"BRAEMAR2":0,"BRAEMAR3":0}},{"t":"2025-12-20T17:55:00","rrp":125.62,"units":{"BRAEMAR1":164.56239,"BRAEMAR2":0,"BRAEMAR3":0}},{"t":"2025-12-20T18:00:00","rrp":123.71,"units":{"BRAEMAR1":164.65631,"BRAEMAR2":0,"BRAEMAR3":0}},{"t":"2025-12-20T18:05:00","rrp":177.81,"units":{"BRAEMAR1":163.69347,"BRAEMAR2":0,"BRAEMAR3":0}},{"t":"2025-12-20T18:10:00","rrp":231.43889,"units":{"BRAEMAR1":165.07903,"BRAEMAR2":0,"BRAEMAR3":0}},{"t":"2025-12-20T18:15:00","rrp":123.71,"units":{"BRAEMAR1":163.34122,"BRAEMAR2":0,"BRAEMAR3":0}},{"t":"2025-12-20T18:20:00","rrp":144.5,"units":{"BRAEMAR1":165.43127,"BRAEMAR2":0,"BRAEMAR3":0}},{"t":"2025-12-20T18:25:00","rrp":177.88,"units":{"BRAEMAR1":161.79126,"BRAEMAR2":0,"BRAEMAR3":0}},{"t":"2025-12-20T18:30:00","rrp":141.73,"units":{"BRAEMAR1":160.96935,"BRAEMAR2":0,"BRAEMAR3":0}},{"t":"2025-12-20T18:35:00","rrp":147.97293,"units":{"BRAEMAR1":164.16316,"BRAEMAR2":0,"BRAEMAR3":0}},{"t":"2025-12-20T18:40:00","rrp":143.94,"units":{"BRAEMAR1":161.2981,"BRAEMAR2":0,"BRAEMAR3":0}},{"t":"2025-12-20T18:45:00","rrp":134.09614,"units":{"BRAEMAR1":163.34122,"BRAEMAR2":0,"BRAEMAR3":0}},{"t":"2025-12-20T18:50:00","rrp":131.73085,"units":{"BRAEMAR1":161.41553,"BRAEMAR2":0,"BRAEMAR3":0}},{"t":"2025-12-20T18:55:00","rrp":143.94,"units":{"BRAEMAR1":163.90485,"BRAEMAR2":0,"BRAEMAR3":0}},{"t":"2025-12-20T19:00:00","rrp":132.05907,"units":{"BRAEMAR1":160.64055,"BRAEMAR2":0,"BRAEMAR3":0}},{"t":"2025-12-20T19:05:00","rrp":141.73,"units":{"BRAEMAR1":164.56239,"BRAEMAR2":0,"BRAEMAR3":0}},{"t":"2025-12-20T19:10:00","rrp":127.75,"units":{"BRAEMAR1":161.1572,"BRAEMAR2":0,"BRAEMAR3":0}},{"t":"2025-12-20T19:15:00","rrp":146.08632,"units":{"BRAEMAR1":162.96548,"BRAEMAR2":0,"BRAEMAR3":0}},{"t":"2025-12-20T19:20:00","rrp":141.73,"units":{"BRAEMAR1":159.93604,"BRAEMAR2":0,"BRAEMAR3":0}},{"t":"2025-12-20T19:25:00","rrp":143.94,"units":{"BRAEMAR1":162.19049,"BRAEMAR2":0,"BRAEMAR3":0}},{"t":"2025-12-20T19:30:00","rrp":128.39,"units":{"BRAEMAR1":160.54663,"BRAEMAR2":0,"BRAEMAR3":0}},{"t":"2025-12-20T19:35:00","rrp":137.95,"units":{"BRAEMAR1":162.04961,"BRAEMAR2":0,"BRAEMAR3":0}},{"t":"2025-12-20T19:40:00","rrp":128.39,"units":{"BRAEMAR1":160.0065,"BRAEMAR2":0,"BRAEMAR3":0}},{"t":"2025-12-20T19:45:00","rrp":129.32,"units":{"BRAEMAR1":161.79126,"BRAEMAR2":0,"BRAEMAR3":0}},{"t":"2025-12-20T19:50:00","rrp":123.71,"units":{"BRAEMAR1":161.11024,"BRAEMAR2":0,"BRAEMAR3":0}},{"t":"2025-12-20T19:55:00","rrp":129.32,"units":{"BRAEMAR1":161.81474,"BRAEMAR2":0,"BRAEMAR3":0}},{"t":"2025-12-20T20:00:00","rrp":141.73,"units":{"BRAEMAR1":163.81088,"BRAEMAR2":0,"BRAEMAR3":0}},{"t":"2025-12-20T20:05:00","rrp":132.1828,"units":{"BRAEMAR1":160.89888,"BRAEMAR2":0,"BRAEMAR3":0}},{"t":"2025-12-20T20:10:00","rrp":141.73,"units":{"BRAEMAR1":163.20032,"BRAEMAR2":0,"BRAEMAR3":0}},{"t":"2025-12-20T20:15:00","rrp":122.73755,"units":{"BRAEMAR1":161.67384,"BRAEMAR2":0,"BRAEMAR3":0}},{"t":"2025-12-20T20:20:00","rrp":122.7,"units":{"BRAEMAR1":162.40186,"BRAEMAR2":0,"BRAEMAR3":0}},{"t":"2025-12-20T20:25:00","rrp":124.11325,"units":{"BRAEMAR1":162.00262,"BRAEMAR2":0,"BRAEMAR3":0}},{"t":"2025-12-20T20:30:00","rrp":107.18668,"units":{"BRAEMAR1":161.06326,"BRAEMAR2":0,"BRAEMAR3":0}},{"t":"2025-12-20T20:35:00","rrp":115.15,"units":{"BRAEMAR1":162.00262,"BRAEMAR2":0,"BRAEMAR3":0}},{"t":"2025-12-20T20:40:00","rrp":126.1415,"units":{"BRAEMAR1":163.99876,"BRAEMAR2":0,"BRAEMAR3":0}},{"t":"2025-12-20T20:45:00","rrp":117.8852,"units":{"BRAEMAR1":161.62689,"BRAEMAR2":0,"BRAEMAR3":0}},{"t":"2025-12-20T20:50:00","rrp":105.69699,"units":{"BRAEMAR1":162.51927,"BRAEMAR2":0,"BRAEMAR3":0}},{"t":"2025-12-20T20:55:00","rrp":125.11127,"units":{"BRAEMAR1":163.69347,"BRAEMAR2":0,"BRAEMAR3":0}},{"t":"2025-12-20T21:00:00","rrp":107.73,"units":{"BRAEMAR1":161.90871,"BRAEMAR2":0,"BRAEMAR3":0}},{"t":"2025-12-20T21:05:00","rrp":105.01424,"units":{"BRAEMAR1":162.16702,"BRAEMAR2":0,"BRAEMAR3":0}},{"t":"2025-12-20T21:10:00","rrp":99.9186,"units":{"BRAEMAR1":162.6132,"BRAEMAR2":0,"BRAEMAR3":0}},{"t":"2025-12-20T21:15:00","rrp":115.15,"units":{"BRAEMAR1":162.63669,"BRAEMAR2":0,"BRAEMAR3":0}},{"t":"2025-12-20T21:20:00","rrp":93.95,"units":{"BRAEMAR1":162.12004,"BRAEMAR2":0,"BRAEMAR3":0}},{"t":"2025-12-20T21:25:00","rrp":99.70578,"units":{"BRAEMAR1":164.06923,"BRAEMAR2":0,"BRAEMAR3":0}},{"t":"2025-12-20T21:30:00","rrp":115.15,"units":{"BRAEMAR1":162.02612,"BRAEMAR2":0,"BRAEMAR3":0}},{"t":"2025-12-20T21:35:00","rrp":121.73,"units":{"BRAEMAR1":161.53293,"BRAEMAR2":0,"BRAEMAR3":0}},{"t":"2025-12-20T21:40:00","rrp":120.38639,"units":{"BRAEMAR1":161.83824,"BRAEMAR2":0,"BRAEMAR3":0}},{"t":"2025-12-20T21:45:00","rrp":110.57209,"units":{"BRAEMAR1":161.46249,"BRAEMAR2":0,"BRAEMAR3":0}},{"t":"2025-12-20T21:50:00","rrp":120.21403,"units":{"BRAEMAR1":163.92833,"BRAEMAR2":0,"BRAEMAR3":0}},{"t":"2025-12-20T21:55:00","rrp":107.73,"units":{"BRAEMAR1":166.51155,"BRAEMAR2":0,"BRAEMAR3":0}},{"t":"2025-12-20T22:00:00","rrp":98.73,"units":{"BRAEMAR1":163.71695,"BRAEMAR2":0,"BRAEMAR3":0}},{"t":"2025-12-20T22:05:00","rrp":79.07702,"units":{"BRAEMAR1":164.56239,"BRAEMAR2":0,"BRAEMAR3":0}},{"t":"2025-12-20T22:10:00","rrp":98.81,"units":{"BRAEMAR1":120.06021,"BRAEMAR2":0,"BRAEMAR3":0}},{"t":"2025-12-20T22:15:00","rrp":115.15,"units":{"BRAEMAR1":69.80443,"BRAEMAR2":0,"BRAEMAR3":0}},{"t":"2025-12-20T22:20:00","rrp":110.58591,"units":{"BRAEMAR1":19.5252,"BRAEMAR2":0,"BRAEMAR3":0}}]},{"date":"2025-12-21","units":{"BRAEMAR1":{"mwh":0,"runIntervals":0,"runRrpWeighted":0,"runMwTotal":0,"revenue":0},"BRAEMAR2":{"mwh":0,"runIntervals":0,"runRrpWeighted":0,"runMwTotal":0,"revenue":0},"BRAEMAR3":{"mwh":0,"runIntervals":0,"runRrpWeighted":0,"runMwTotal":0,"revenue":0}},"intervals":[]},{"date":"2025-12-22","units":{"BRAEMAR1":{"mwh":666.1300408333333,"runIntervals":57,"runRrpWeighted":1178424.0883175319,"runMwTotal":7993.56049,"revenue":98202.00735979427},"BRAEMAR2":{"mwh":576.4723266666664,"runIntervals":55,"runRrpWeighted":946205.6669551476,"runMwTotal":6917.66792,"revenue":78850.47224626224},"BRAEMAR3":{"mwh":0,"runIntervals":0,"runRrpWeighted":0,"runMwTotal":0,"revenue":0}},"intervals":[{"t":"2025-12-22T16:35:00","rrp":61.20364,"units":{"BRAEMAR1":22.27282,"BRAEMAR2":0,"BRAEMAR3":0}},{"t":"2025-12-22T16:40:00","rrp":122.57,"units":{"BRAEMAR1":72.81039,"BRAEMAR2":0,"BRAEMAR3":0}},{"t":"2025-12-22T16:45:00","rrp":122.57,"units":{"BRAEMAR1":111.25371,"BRAEMAR2":0,"BRAEMAR3":0}},{"t":"2025-12-22T16:50:00","rrp":88.97736,"units":{"BRAEMAR1":109.70377,"BRAEMAR2":0,"BRAEMAR3":0}},{"t":"2025-12-22T16:55:00","rrp":89.24308,"units":{"BRAEMAR1":108.95227,"BRAEMAR2":0,"BRAEMAR3":0}},{"t":"2025-12-22T17:00:00","rrp":133,"units":{"BRAEMAR1":109.3515,"BRAEMAR2":0,"BRAEMAR3":0}},{"t":"2025-12-22T17:05:00","rrp":144.55,"units":{"BRAEMAR1":118.83904,"BRAEMAR2":0,"BRAEMAR3":0}},{"t":"2025-12-22T17:10:00","rrp":144.55,"units":{"BRAEMAR1":161.53293,"BRAEMAR2":0,"BRAEMAR3":0}},{"t":"2025-12-22T17:15:00","rrp":144.5,"units":{"BRAEMAR1":162.87152,"BRAEMAR2":0,"BRAEMAR3":0}},{"t":"2025-12-22T17:20:00","rrp":144.55,"units":{"BRAEMAR1":162.77759,"BRAEMAR2":0,"BRAEMAR3":0}},{"t":"2025-12-22T17:25:00","rrp":177.81,"units":{"BRAEMAR1":162.49579,"BRAEMAR2":0,"BRAEMAR3":0}},{"t":"2025-12-22T17:30:00","rrp":188.22,"units":{"BRAEMAR1":162.44884,"BRAEMAR2":0,"BRAEMAR3":0}},{"t":"2025-12-22T17:35:00","rrp":240.73,"units":{"BRAEMAR1":162.7541,"BRAEMAR2":0,"BRAEMAR3":0}},{"t":"2025-12-22T17:40:00","rrp":240.73,"units":{"BRAEMAR1":162.80109,"BRAEMAR2":0,"BRAEMAR3":0}},{"t":"2025-12-22T17:45:00","rrp":177.81,"units":{"BRAEMAR1":162.9185,"BRAEMAR2":42.16378,"BRAEMAR3":0}},{"t":"2025-12-22T17:50:00","rrp":253.67224,"units":{"BRAEMAR1":162.9185,"BRAEMAR2":82.22748,"BRAEMAR3":0}},{"t":"2025-12-22T17:55:00","rrp":177.9,"units":{"BRAEMAR1":163.24728,"BRAEMAR2":131.23859,"BRAEMAR3":0}},{"t":"2025-12-22T18:00:00","rrp":235.75,"units":{"BRAEMAR1":163.5291,"BRAEMAR2":162.56625,"BRAEMAR3":0}},{"t":"2025-12-22T18:05:00","rrp":177.9,"units":{"BRAEMAR1":161.86172,"BRAEMAR2":160.80495,"BRAEMAR3":0}},{"t":"2025-12-22T18:10:00","rrp":177.9,"units":{"BRAEMAR1":161.93216,"BRAEMAR2":159.8186,"BRAEMAR3":0}},{"t":"2025-12-22T18:15:00","rrp":177.81,"units":{"BRAEMAR1":164.04575,"BRAEMAR2":163.45863,"BRAEMAR3":0}},{"t":"2025-12-22T18:20:00","rrp":177.81,"units":{"BRAEMAR1":163.99876,"BRAEMAR2":162.02612,"BRAEMAR3":0}},{"t":"2025-12-22T18:25:00","rrp":144.5,"units":{"BRAEMAR1":164.13968,"BRAEMAR2":161.72083,"BRAEMAR3":0}},{"t":"2025-12-22T18:30:00","rrp":143.94,"units":{"BRAEMAR1":164.18665,"BRAEMAR2":163.2238,"BRAEMAR3":0}},{"t":"2025-12-22T18:35:00","rrp":135,"units":{"BRAEMAR1":163.50562,"BRAEMAR2":161.25113,"BRAEMAR3":0}},{"t":"2025-12-22T18:40:00","rrp":136.83,"units":{"BRAEMAR1":164.37451,"BRAEMAR2":146.15094,"BRAEMAR3":0}},{"t":"2025-12-22T18:45:00","rrp":136.82995,"units":{"BRAEMAR1":163.92833,"BRAEMAR2":161.86172,"BRAEMAR3":0}},{"t":"2025-12-22T18:50:00","rrp":136.83,"units":{"BRAEMAR1":164.65631,"BRAEMAR2":162.70715,"BRAEMAR3":0}},{"t":"2025-12-22T18:55:00","rrp":136.83006,"units":{"BRAEMAR1":164.65631,"BRAEMAR2":163.03592,"BRAEMAR3":0}},{"t":"2025-12-22T19:00:00","rrp":136.83006,"units":{"BRAEMAR1":164.86769,"BRAEMAR2":163.95178,"BRAEMAR3":0}},{"t":"2025-12-22T19:05:00","rrp":141.73,"units":{"BRAEMAR1":163.90485,"BRAEMAR2":161.60341,"BRAEMAR3":0}},{"t":"2025-12-22T19:10:00","rrp":136.82,"units":{"BRAEMAR1":162.9185,"BRAEMAR2":160.80495,"BRAEMAR3":0}},{"t":"2025-12-22T19:15:00","rrp":135,"units":{"BRAEMAR1":164.86769,"BRAEMAR2":164.75024,"BRAEMAR3":0}},{"t":"2025-12-22T19:20:00","rrp":131.4846,"units":{"BRAEMAR1":165.12601,"BRAEMAR2":164.53889,"BRAEMAR3":0}},{"t":"2025-12-22T19:25:00","rrp":135,"units":{"BRAEMAR1":114.04829,"BRAEMAR2":114.07178,"BRAEMAR3":0}},{"t":"2025-12-22T19:30:00","rrp":133.91252,"units":{"BRAEMAR1":166.1593,"BRAEMAR2":161.83824,"BRAEMAR3":0}},{"t":"2025-12-22T19:35:00","rrp":135,"units":{"BRAEMAR1":165.36084,"BRAEMAR2":116.25578,"BRAEMAR3":0}},{"t":"2025-12-22T19:40:00","rrp":137.75,"units":{"BRAEMAR1":164.98511,"BRAEMAR2":133.25821,"BRAEMAR3":0}},{"t":"2025-12-22T19:45:00","rrp":136.82,"units":{"BRAEMAR1":165.854,"BRAEMAR2":154.29987,"BRAEMAR3":0}},{"t":"2025-12-22T19:50:00","rrp":135,"units":{"BRAEMAR1":164.91464,"BRAEMAR2":164.82071,"BRAEMAR3":0}},{"t":"2025-12-22T19:55:00","rrp":133.19577,"units":{"BRAEMAR1":164.49191,"BRAEMAR2":154.84,"BRAEMAR3":0}},{"t":"2025-12-22T20:00:00","rrp":133,"units":{"BRAEMAR1":164.75024,"BRAEMAR2":108.43562,"BRAEMAR3":0}},{"t":"2025-12-22T20:05:00","rrp":128.39,"units":{"BRAEMAR1":160.82843,"BRAEMAR2":110.12648,"BRAEMAR3":0}},{"t":"2025-12-22T20:10:00","rrp":130.05029,"units":{"BRAEMAR1":111.86429,"BRAEMAR2":108.36517,"BRAEMAR3":0}},{"t":"2025-12-22T20:15:00","rrp":128.39,"units":{"BRAEMAR1":109.06969,"BRAEMAR2":109.0462,"BRAEMAR3":0}},{"t":"2025-12-22T20:20:00","rrp":128.39,"units":{"BRAEMAR1":108.88182,"BRAEMAR2":108.99924,"BRAEMAR3":0}},{"t":"2025-12-22T20:25:00","rrp":134.55754,"units":{"BRAEMAR1":111.01886,"BRAEMAR2":111.04234,"BRAEMAR3":0}},{"t":"2025-12-22T20:30:00","rrp":134.48724,"units":{"BRAEMAR1":158.01035,"BRAEMAR2":110.83099,"BRAEMAR3":0}},{"t":"2025-12-22T20:35:00","rrp":116.04736,"units":{"BRAEMAR1":158.92622,"BRAEMAR2":108.52956,"BRAEMAR3":0}},{"t":"2025-12-22T20:40:00","rrp":104.55,"units":{"BRAEMAR1":125.39107,"BRAEMAR2":110.69008,"BRAEMAR3":0}},{"t":"2025-12-22T20:45:00","rrp":121.73,"units":{"BRAEMAR1":108.99924,"BRAEMAR2":109.16364,"BRAEMAR3":0}},{"t":"2025-12-22T20:50:00","rrp":104.55,"units":{"BRAEMAR1":109.0462,"BRAEMAR2":109.51588,"BRAEMAR3":0}},{"t":"2025-12-22T20:55:00","rrp":121.73,"units":{"BRAEMAR1":108.67046,"BRAEMAR2":108.71744,"BRAEMAR3":0}},{"t":"2025-12-22T21:00:00","rrp":98.81,"units":{"BRAEMAR1":108.29472,"BRAEMAR2":108.29472,"BRAEMAR3":0}},{"t":"2025-12-22T21:05:00","rrp":104.55,"units":{"BRAEMAR1":108.74091,"BRAEMAR2":108.74091,"BRAEMAR3":0}},{"t":"2025-12-22T21:10:00","rrp":104.55,"units":{"BRAEMAR1":57.33444,"BRAEMAR2":108.60001,"BRAEMAR3":0}},{"t":"2025-12-22T21:15:00","rrp":122.52,"units":{"BRAEMAR1":11.47018,"BRAEMAR2":109.96208,"BRAEMAR3":0}},{"t":"2025-12-22T21:20:00","rrp":98.71,"units":{"BRAEMAR1":0,"BRAEMAR2":108.60001,"BRAEMAR3":0}},{"t":"2025-12-22T21:25:00","rrp":98.81,"units":{"BRAEMAR1":0,"BRAEMAR2":111.81731,"BRAEMAR3":0}},{"t":"2025-12-22T21:30:00","rrp":104.55,"units":{"BRAEMAR1":0,"BRAEMAR2":108.48259,"BRAEMAR3":0}},{"t":"2025-12-22T21:35:00","rrp":122.52,"units":{"BRAEMAR1":0,"BRAEMAR2":108.95227,"BRAEMAR3":0}},{"t":"2025-12-22T21:40:00","rrp":122.52,"units":{"BRAEMAR1":0,"BRAEMAR2":109.68027,"BRAEMAR3":0}},{"t":"2025-12-22T21:45:00","rrp":98.81,"units":{"BRAEMAR1":0,"BRAEMAR2":108.29472,"BRAEMAR3":0}},{"t":"2025-12-22T21:50:00","rrp":115.13006,"units":{"BRAEMAR1":0,"BRAEMAR2":110.05603,"BRAEMAR3":0}},{"t":"2025-12-22T21:55:00","rrp":121.73,"units":{"BRAEMAR1":0,"BRAEMAR2":108.85832,"BRAEMAR3":0}},{"t":"2025-12-22T22:00:00","rrp":97.27114,"units":{"BRAEMAR1":0,"BRAEMAR2":108.24774,"BRAEMAR3":0}},{"t":"2025-12-22T22:05:00","rrp":121.73,"units":{"BRAEMAR1":0,"BRAEMAR2":111.84081,"BRAEMAR3":0}},{"t":"2025-12-22T22:10:00","rrp":128.39,"units":{"BRAEMAR1":0,"BRAEMAR2":61.86684,"BRAEMAR3":0}},{"t":"2025-12-22T22:15:00","rrp":115.15,"units":{"BRAEMAR1":0,"BRAEMAR2":12.6209,"BRAEMAR3":0}}]},{"date":"2025-12-23","units":{"BRAEMAR1":{"mwh":502.8927491666667,"runIntervals":57,"runRrpWeighted":590718.1309413424,"runMwTotal":6034.712990000001,"revenue":49226.51091177854},"BRAEMAR2":{"mwh":0,"runIntervals":0,"runRrpWeighted":0,"runMwTotal":0,"revenue":0},"BRAEMAR3":{"mwh":0,"runIntervals":0,"runRrpWeighted":0,"runMwTotal":0,"revenue":0}},"intervals":[{"t":"2025-12-23T16:05:00","rrp":104.55,"units":{"BRAEMAR1":51.58086,"BRAEMAR2":0,"BRAEMAR3":0}},{"t":"2025-12-23T16:10:00","rrp":113.53001,"units":{"BRAEMAR1":104.70166,"BRAEMAR2":0,"BRAEMAR3":0}},{"t":"2025-12-23T16:15:00","rrp":49.56,"units":{"BRAEMAR1":113.95436,"BRAEMAR2":0,"BRAEMAR3":0}},{"t":"2025-12-23T16:20:00","rrp":73.29,"units":{"BRAEMAR1":112.28699,"BRAEMAR2":0,"BRAEMAR3":0}},{"t":"2025-12-23T16:25:00","rrp":49.56,"units":{"BRAEMAR1":110.8075,"BRAEMAR2":0,"BRAEMAR3":0}},{"t":"2025-12-23T16:30:00","rrp":73.29,"units":{"BRAEMAR1":108.92879,"BRAEMAR2":0,"BRAEMAR3":0}},{"t":"2025-12-23T16:35:00","rrp":98.81,"units":{"BRAEMAR1":110.83099,"BRAEMAR2":0,"BRAEMAR3":0}},{"t":"2025-12-23T16:40:00","rrp":125.62,"units":{"BRAEMAR1":107.96594,"BRAEMAR2":0,"BRAEMAR3":0}},{"t":"2025-12-23T16:45:00","rrp":93,"units":{"BRAEMAR1":109.56285,"BRAEMAR2":0,"BRAEMAR3":0}},{"t":"2025-12-23T16:50:00","rrp":64.86985,"units":{"BRAEMAR1":110.10298,"BRAEMAR2":0,"BRAEMAR3":0}},{"t":"2025-12-23T16:55:00","rrp":73.29,"units":{"BRAEMAR1":110.05603,"BRAEMAR2":0,"BRAEMAR3":0}},{"t":"2025-12-23T17:00:00","rrp":73.7,"units":{"BRAEMAR1":108.31819,"BRAEMAR2":0,"BRAEMAR3":0}},{"t":"2025-12-23T17:05:00","rrp":73.7,"units":{"BRAEMAR1":111.30067,"BRAEMAR2":0,"BRAEMAR3":0}},{"t":"2025-12-23T17:10:00","rrp":93.94999,"units":{"BRAEMAR1":110.0795,"BRAEMAR2":0,"BRAEMAR3":0}},{"t":"2025-12-23T17:15:00","rrp":93.72996,"units":{"BRAEMAR1":107.26141,"BRAEMAR2":0,"BRAEMAR3":0}},{"t":"2025-12-23T17:20:00","rrp":98.81,"units":{"BRAEMAR1":107.82504,"BRAEMAR2":0,"BRAEMAR3":0}},{"t":"2025-12-23T17:25:00","rrp":95.75,"units":{"BRAEMAR1":110.57266,"BRAEMAR2":0,"BRAEMAR3":0}},{"t":"2025-12-23T17:30:00","rrp":121.73,"units":{"BRAEMAR1":110.05603,"BRAEMAR2":0,"BRAEMAR3":0}},{"t":"2025-12-23T17:35:00","rrp":115.15,"units":{"BRAEMAR1":108.57654,"BRAEMAR2":0,"BRAEMAR3":0}},{"t":"2025-12-23T17:40:00","rrp":115.15,"units":{"BRAEMAR1":108.67046,"BRAEMAR2":0,"BRAEMAR3":0}},{"t":"2025-12-23T17:45:00","rrp":103.89,"units":{"BRAEMAR1":108.64699,"BRAEMAR2":0,"BRAEMAR3":0}},{"t":"2025-12-23T17:50:00","rrp":104.55,"units":{"BRAEMAR1":108.97575,"BRAEMAR2":0,"BRAEMAR3":0}},{"t":"2025-12-23T17:55:00","rrp":103.89,"units":{"BRAEMAR1":108.15381,"BRAEMAR2":0,"BRAEMAR3":0}},{"t":"2025-12-23T18:00:00","rrp":98.73,"units":{"BRAEMAR1":108.85832,"BRAEMAR2":0,"BRAEMAR3":0}},{"t":"2025-12-23T18:05:00","rrp":93.74,"units":{"BRAEMAR1":108.08336,"BRAEMAR2":0,"BRAEMAR3":0}},{"t":"2025-12-23T18:10:00","rrp":93.95,"units":{"BRAEMAR1":107.61368,"BRAEMAR2":0,"BRAEMAR3":0}},{"t":"2025-12-23T18:15:00","rrp":98.73,"units":{"BRAEMAR1":109.16364,"BRAEMAR2":0,"BRAEMAR3":0}},{"t":"2025-12-23T18:20:00","rrp":95.75,"units":{"BRAEMAR1":110.87796,"BRAEMAR2":0,"BRAEMAR3":0}},{"t":"2025-12-23T18:25:00","rrp":122.7,"units":{"BRAEMAR1":112.14609,"BRAEMAR2":0,"BRAEMAR3":0}},{"t":"2025-12-23T18:30:00","rrp":123.71,"units":{"BRAEMAR1":110.61963,"BRAEMAR2":0,"BRAEMAR3":0}},{"t":"2025-12-23T18:35:00","rrp":122.7,"units":{"BRAEMAR1":109.09317,"BRAEMAR2":0,"BRAEMAR3":0}},{"t":"2025-12-23T18:40:00","rrp":93,"units":{"BRAEMAR1":111.77036,"BRAEMAR2":0,"BRAEMAR3":0}},{"t":"2025-12-23T18:45:00","rrp":93.95003,"units":{"BRAEMAR1":110.03253,"BRAEMAR2":0,"BRAEMAR3":0}},{"t":"2025-12-23T18:50:00","rrp":98.73,"units":{"BRAEMAR1":111.39461,"BRAEMAR2":0,"BRAEMAR3":0}},{"t":"2025-12-23T18:55:00","rrp":104.55,"units":{"BRAEMAR1":108.13033,"BRAEMAR2":0,"BRAEMAR3":0}},{"t":"2025-12-23T19:00:00","rrp":98.81,"units":{"BRAEMAR1":108.67046,"BRAEMAR2":0,"BRAEMAR3":0}},{"t":"2025-12-23T19:05:00","rrp":95.75,"units":{"BRAEMAR1":108.43562,"BRAEMAR2":0,"BRAEMAR3":0}},{"t":"2025-12-23T19:10:00","rrp":121.73,"units":{"BRAEMAR1":108.71744,"BRAEMAR2":0,"BRAEMAR3":0}},{"t":"2025-12-23T19:15:00","rrp":98.81,"units":{"BRAEMAR1":108.62349,"BRAEMAR2":0,"BRAEMAR3":0}},{"t":"2025-12-23T19:20:00","rrp":93.73,"units":{"BRAEMAR1":110.71358,"BRAEMAR2":0,"BRAEMAR3":0}},{"t":"2025-12-23T19:25:00","rrp":93,"units":{"BRAEMAR1":109.02272,"BRAEMAR2":0,"BRAEMAR3":0}},{"t":"2025-12-23T19:30:00","rrp":93.73,"units":{"BRAEMAR1":108.85832,"BRAEMAR2":0,"BRAEMAR3":0}},{"t":"2025-12-23T19:35:00","rrp":93.95003,"units":{"BRAEMAR1":109.21059,"BRAEMAR2":0,"BRAEMAR3":0}},{"t":"2025-12-23T19:40:00","rrp":98.81,"units":{"BRAEMAR1":107.96594,"BRAEMAR2":0,"BRAEMAR3":0}},{"t":"2025-12-23T19:45:00","rrp":98.73,"units":{"BRAEMAR1":108.48259,"BRAEMAR2":0,"BRAEMAR3":0}},{"t":"2025-12-23T19:50:00","rrp":103.99,"units":{"BRAEMAR1":108.69395,"BRAEMAR2":0,"BRAEMAR3":0}},{"t":"2025-12-23T19:55:00","rrp":103.99,"units":{"BRAEMAR1":108.67046,"BRAEMAR2":0,"BRAEMAR3":0}},{"t":"2025-12-23T20:00:00","rrp":98.73,"units":{"BRAEMAR1":110.59616,"BRAEMAR2":0,"BRAEMAR3":0}},{"t":"2025-12-23T20:05:00","rrp":120,"units":{"BRAEMAR1":108.88182,"BRAEMAR2":0,"BRAEMAR3":0}},{"t":"2025-12-23T20:10:00","rrp":101.07049,"units":{"BRAEMAR1":108.01291,"BRAEMAR2":0,"BRAEMAR3":0}},{"t":"2025-12-23T20:15:00","rrp":103.99,"units":{"BRAEMAR1":109.11667,"BRAEMAR2":0,"BRAEMAR3":0}},{"t":"2025-12-23T20:20:00","rrp":120,"units":{"BRAEMAR1":111.60597,"BRAEMAR2":0,"BRAEMAR3":0}},{"t":"2025-12-23T20:25:00","rrp":93.73,"units":{"BRAEMAR1":108.67046,"BRAEMAR2":0,"BRAEMAR3":0}},{"t":"2025-12-23T20:30:00","rrp":88.80898,"units":{"BRAEMAR1":110.43176,"BRAEMAR2":0,"BRAEMAR3":0}},{"t":"2025-12-23T20:35:00","rrp":98.81,"units":{"BRAEMAR1":109.51588,"BRAEMAR2":0,"BRAEMAR3":0}},{"t":"2025-12-23T20:40:00","rrp":125.62,"units":{"BRAEMAR1":62.17213,"BRAEMAR2":0,"BRAEMAR3":0}},{"t":"2025-12-23T20:45:00","rrp":115.15,"units":{"BRAEMAR1":12.64439,"BRAEMAR2":0,"BRAEMAR3":0}}]},{"date":"2025-12-24","units":{"BRAEMAR1":{"mwh":0,"runIntervals":0,"runRrpWeighted":0,"runMwTotal":0,"revenue":0},"BRAEMAR2":{"mwh":0,"runIntervals":0,"runRrpWeighted":0,"runMwTotal":0,"revenue":0},"BRAEMAR3":{"mwh":0,"runIntervals":0,"runRrpWeighted":0,"runMwTotal":0,"revenue":0}},"intervals":[]},{"date":"2025-12-25","units":{"BRAEMAR1":{"mwh":0,"runIntervals":0,"runRrpWeighted":0,"runMwTotal":0,"revenue":0},"BRAEMAR2":{"mwh":0,"runIntervals":0,"runRrpWeighted":0,"runMwTotal":0,"revenue":0},"BRAEMAR3":{"mwh":0,"runIntervals":0,"runRrpWeighted":0,"runMwTotal":0,"revenue":0}},"intervals":[]},{"date":"2025-12-26","units":{"BRAEMAR1":{"mwh":0,"runIntervals":0,"runRrpWeighted":0,"runMwTotal":0,"revenue":0},"BRAEMAR2":{"mwh":0,"runIntervals":0,"runRrpWeighted":0,"runMwTotal":0,"revenue":0},"BRAEMAR3":{"mwh":0,"runIntervals":0,"runRrpWeighted":0,"runMwTotal":0,"revenue":0}},"intervals":[]},{"date":"2025-12-27","units":{"BRAEMAR1":{"mwh":0,"runIntervals":0,"runRrpWeighted":0,"runMwTotal":0,"revenue":0},"BRAEMAR2":{"mwh":0,"runIntervals":0,"runRrpWeighted":0,"runMwTotal":0,"revenue":0},"BRAEMAR3":{"mwh":0,"runIntervals":0,"runRrpWeighted":0,"runMwTotal":0,"revenue":0}},"intervals":[]},{"date":"2025-12-28","units":{"BRAEMAR1":{"mwh":0,"runIntervals":0,"runRrpWeighted":0,"runMwTotal":0,"revenue":0},"BRAEMAR2":{"mwh":0,"runIntervals":0,"runRrpWeighted":0,"runMwTotal":0,"revenue":0},"BRAEMAR3":{"mwh":0,"runIntervals":0,"runRrpWeighted":0,"runMwTotal":0,"revenue":0}},"intervals":[]},{"date":"2025-12-29","units":{"BRAEMAR1":{"mwh":0,"runIntervals":0,"runRrpWeighted":0,"runMwTotal":0,"revenue":0},"BRAEMAR2":{"mwh":0,"runIntervals":0,"runRrpWeighted":0,"runMwTotal":0,"revenue":0},"BRAEMAR3":{"mwh":0,"runIntervals":0,"runRrpWeighted":0,"runMwTotal":0,"revenue":0}},"intervals":[]},{"date":"2025-12-30","units":{"BRAEMAR1":{"mwh":0,"runIntervals":0,"runRrpWeighted":0,"runMwTotal":0,"revenue":0},"BRAEMAR2":{"mwh":0,"runIntervals":0,"runRrpWeighted":0,"runMwTotal":0,"revenue":0},"BRAEMAR3":{"mwh":0,"runIntervals":0,"runRrpWeighted":0,"runMwTotal":0,"revenue":0}},"intervals":[]},{"date":"2025-12-31","units":{"BRAEMAR1":{"mwh":0,"runIntervals":0,"runRrpWeighted":0,"runMwTotal":0,"revenue":0},"BRAEMAR2":{"mwh":0,"runIntervals":0,"runRrpWeighted":0,"runMwTotal":0,"revenue":0},"BRAEMAR3":{"mwh":0,"runIntervals":0,"runRrpWeighted":0,"runMwTotal":0,"revenue":0}},"intervals":[]}]}
